medium1_multiply/__init__.py
medium1_multiply/mul.py
medium1_multiply-0.1.0.dist-info/METADATA
medium1_multiply-0.1.0.dist-info/WHEEL
medium1_multiply-0.1.0.dist-info/top_level.txt
medium1_multiply-0.1.0.dist-info/RECORD
